PyOpenGLtoolbox/__init__.py
PyOpenGLtoolbox/about.py
PyOpenGLtoolbox/camera.py
PyOpenGLtoolbox/figures.py
PyOpenGLtoolbox/geometry.py
PyOpenGLtoolbox/materials.py
PyOpenGLtoolbox/mathlib.py
PyOpenGLtoolbox/opengl.py
PyOpenGLtoolbox/particles.py
PyOpenGLtoolbox/pyopengl.py
PyOpenGLtoolbox/shader.py
PyOpenGLtoolbox/textures.py
PyOpenGLtoolbox/utils.py
PyOpenGL_toolbox-2.3.0.dist-info/LICENSE
PyOpenGL_toolbox-2.3.0.dist-info/METADATA
PyOpenGL_toolbox-2.3.0.dist-info/WHEEL
PyOpenGL_toolbox-2.3.0.dist-info/top_level.txt
PyOpenGL_toolbox-2.3.0.dist-info/RECORD
