Metadata-Version: 2.1
Name: PyOpenGL-toolbox
Version: 2.3.0
Summary: PyOpenGL toolbox
Home-page: https://github.com/ppizarror/pyopengl-toolbox
Author: Pablo Pizarro @ppizarror.com
Author-email: pablo.pizarro@ing.uchile.cl
License: MIT
Platform: UNKNOWN
Classifier: License :: OSI Approved :: MIT License
Classifier: Operating System :: OS Independent
Classifier: Programming Language :: Python
Classifier: Topic :: Software Development :: Libraries :: pygame
Requires-Dist: numpy
Requires-Dist: Pillow
Requires-Dist: pygame
Requires-Dist: PyOpenGL
